{
  "empresa_id": "456",
  "paciente_id": "789",
  "puesto": "Supervisor",
  "area": "Calidad",
  "fecha_ingreso": "2019-06-10",
  "antiguedad": "4 años, 6 meses",
  "antiguedad_calculada": "4 años, 6 meses",
  "antiguedad_anios": 4,
  "antiguedad_meses": 6,
  "obra_social": "Swiss Medical",
  "plan": "Premium",
  "nro_afiliado": "987654321",
  "tipo_licencia": "ART",
  "agente_causal": "Herramienta",
  "diagnostico": "Lumbalgia aguda por sobreesfuerzo",
  "partes_afectadas": [
    "espalda_baja",
    "columna_lumbar"
  ],
  "tratamiento": "Reposo relativo, antiinflamatorios, fisioterapia. Se indica kinesiología 3 veces por semana.",
  "aseguradora_art": "Si",
  "inicio_certificado": "2024-01-05",
  "vto_certificado": "2024-01-20",
  "dias_ausentismo": 16,
  "dia_inicio_cert": "Viernes",
  "med_tratante": "Dr. Carlos Fernández",
  "matricula": "MP-54321",
  "especialidad": "Traumatólogo",
  "nro_denuncia_art": "ART-2024-001234",
  "tipo_denuncia_art": "Accidente de trabajo",
  "fecha_control": "2024-01-18",
  "med_auditor": "Dr. Laura Morales",
  "resultado": "Convalidado",
  "requiere_reubicacion": "No",
  "apto_reingreso": "2024-01-21",
  "alta_reingreso": "2024-01-21",
  "dias_ausentismo_control": 16,
  "observaciones": "El paciente presenta buena evolución. Se recomienda reincorporación progresiva con restricciones de carga pesada por 30 días.",
  "fecha_registro": "2024-01-18T14:45:00.000Z"
} 